[
    {
        "pk": 1, 
        "model": "events.day", 
        "fields": {
            "name": "Wednesday, 20th"
        }
    }, 
    {
        "pk": 2, 
        "model": "events.day", 
        "fields": {
            "name": "Thursday, 21st"
        }
    },
    {
        "pk": 3, 
        "model": "events.day", 
        "fields": {
            "name": "Friday, 22nd"
        }
    },
    {
        "pk": 4, 
        "model": "events.day", 
        "fields": {
            "name": "Saturday, 23rd"
        }
    },
    {
        "pk": 5, 
        "model": "events.day", 
        "fields": {
            "name": "Sunday, 24th"
        }
    }
]